dash_picture_annotation/DashPictureAnnotation.py
dash_picture_annotation/__init__.py
dash_picture_annotation/_imports_.py
dash_picture_annotation/async-DashPictureAnnotation.js
dash_picture_annotation/async-DashPictureAnnotation.js.map
dash_picture_annotation/dash_picture_annotation.min.js
dash_picture_annotation/dash_picture_annotation.min.js.map
dash_picture_annotation/metadata.json
dash_picture_annotation/package-info.json
dash_picture_annotation/typehints.py
dash_picture_annotation/utilities.py
dash_picture_annotation-0.2.1.dist-info/LICENSE
dash_picture_annotation-0.2.1.dist-info/METADATA
dash_picture_annotation-0.2.1.dist-info/WHEEL
dash_picture_annotation-0.2.1.dist-info/top_level.txt
dash_picture_annotation-0.2.1.dist-info/RECORD
